MANIFEST.in
README.rst
setup.cfg
setup.py
shapeit/__init__.py
shapeit/errors.py
shapeit/measure.py
shapeit/srs.py
shapeit/types.py
shapeit/version.py
shapeit/xchg.py
shapeit.egg-info/PKG-INFO
shapeit.egg-info/SOURCES.txt
shapeit.egg-info/dependency_links.txt
shapeit.egg-info/entry_points.txt
shapeit.egg-info/requires.txt
shapeit.egg-info/top_level.txt
shapeit/geometry/__init__.py
shapeit/geometry/base.py
shapeit/geometry/multi.py