Metadata-Version: 1.2
Name: shapeit
Version: 0.0.6
Summary: It's Shapely with projections and some other conveniences!
Home-page: https://github.com/patdaburu/shapeit
Author: Pat Daburu
Author-email: pat@daburu.net
License: MIT
Download-URL: https://github.com/patdaburu/shapeit/archive/0.0.6.tar.gz
Platform: UNKNOWN
Classifier: Development Status :: 3 - Alpha
Classifier: Intended Audience :: Developers
Classifier: Topic :: Software Development :: Libraries
Classifier: License :: OSI Approved :: MIT License
Classifier: Programming Language :: Python :: 3.6
Requires-Python: >=0.0.1
